hueify/__init__.py
hueify/bridge.py
hueify/main.py
hueify/controllers/group_scene_controller.py
hueify/controllers/group/group_controller.py
hueify/controllers/group/group_controller_factory.py
hueify/controllers/group/group_state_repository.py
hueify/controllers/group/groups_manager.py
hueify/models/group_info.py
hueify-0.1.5.dist-info/licenses/LICENSE
hueify-0.1.5.dist-info/METADATA
hueify-0.1.5.dist-info/WHEEL
hueify-0.1.5.dist-info/top_level.txt
hueify-0.1.5.dist-info/RECORD
