Metadata-Version: 2.4
Name: hueify
Version: 0.1.5
Summary: Python bib to control Philips Hue lights and groups.
Home-page: https://github.com/mathisarends/hueify
Author: Mathis Arends
License: MIT
Classifier: Programming Language :: Python :: 3
Classifier: License :: OSI Approved :: MIT License
Requires-Python: >=3.7
License-File: LICENSE
Requires-Dist: aiohttp>=3.11.0
Requires-Dist: python-dotenv>=1.0.0
Requires-Dist: rapidfuzz==3.13.0
Dynamic: author
Dynamic: classifier
Dynamic: home-page
Dynamic: license
Dynamic: license-file
Dynamic: requires-dist
Dynamic: requires-python
Dynamic: summary
